{"sections":{"1661619382b4020fa2":{"type":"rich-text","blocks":{"166161938159ca8988-1":{"type":"heading","settings":{"text":"CONTACT US","marker_style":"style1","size":"h2","marker_color":"#FD6262"}}},"block_order":["166161938159ca8988-1"],"settings":{"text_width":"medium","text_position":"center","text_alignment":"center","color_bg":"rgba(0,0,0,0)","color_heading":"#1a1c1d","color_text":"#151515","color_links":"#151515","disable_top_spacing":false,"disable_bottom_spacing":true}},"1652268757b7c53383":{"type":"contact-form","settings":{"heading":"","marker_style":"style1","description":"","show_phone_number":true,"marker_color":"#FD6262","disable_top_spacing":true,"disable_bottom_spacing":false}}},"order":["1661619382b4020fa2","1652268757b7c53383"]}